<?xml version="1.0" encoding="UTF-8"?>
<java version="1.8.0_101" class="java.beans.XMLDecoder">

	<object	class="br.com.uoutec.ediacaran.web.tomcat.TomcatServerBootstrap">
	
		<void property="listenerManager">
			<object class="br.com.uoutec.ediacaran.core.EdiacaranListenerManagerImp">
				<void method="addListener">
					<object class="br.com.uoutec.ediacaran.weld.tomcat.TomcatRegisterContainerEventListener"/>
				</void>
				
				<void method="addListener">
					<object class="br.com.uoutec.ediacaran.web.tomcat.TomcatContextListener"/>
				</void>

				<void method="addListener">
					<object class="br.com.uoutec.ediacaran.weld.context.ActiveRequestContextBridgeListener"/>
				</void>

				<void method="addListener">
					<object class="br.com.uoutec.ediacaran.weld.context.ActiveSessionContextBridgeListener"/>
				</void>
			
				<!--				
				<void method="addListener">
					<object class="br.com.uoutec.ediacaran.ProxyEdiacaranEventListener">
						<void method="setEventListerClass">
							<string>br.com.uoutec.ediacaran.system.WebEdiacaranListener</string>
						</void>
					</object>
				</void>

				<void method="addListener">
					<object class="br.com.uoutec.ediacaran.ProxyEdiacaranEventListener">
						<void method="setEventListerClass">
							<string>br.com.uoutec.ediacaran.core.system.listener.EntityInheritanceListener</string>
						</void>
					</object>
				</void>
				
				<void method="addListener">
					<object class="br.com.uoutec.ediacaran.ProxyEdiacaranEventListener">
						<void method="setEventListerClass">
							<string>br.com.uoutec.ediacaran.core.system.listener.LanguageListener</string>
						</void>
					</object>
				</void>

				<void method="addListener">
					<object class="br.com.uoutec.ediacaran.ProxyEdiacaranEventListener">
						<void method="setEventListerClass">
							<string>br.com.uoutec.ediacaran.core.system.listener.FilterListener</string>
						</void>
					</object>
				</void>
				-->			
			</object>
		</void>

		<void property="securityPolicyManager">
			<object class="br.com.uoutec.ediacaran.core.SecurityPolicyManagerImp">
			
				<void property="policyFileWriter">
					<object class="br.com.uoutec.ediacaran.web.WebPolicyFileWriterImp"/>
				</void>
				
				<void method="addDefaultSecurityPermission">
					<string>runtime</string>
					<string>method.java.lang.System.arraycopy</string>
					<string/>
				</void>
				
				<void method="addDefaultSecurityPermission">
					<string>runtime</string>
					<string>method.java.lang.System.currentTimeMillis</string>
					<string/>
				</void>
				
				<void method="addDefaultSecurityPermission">
					<string>runtime</string>
					<string>method.java.lang.Thread.currentThread</string>
					<string/>
				</void>
				
				<void method="addDefaultSecurityPermission">
					<string>runtime</string>
					<string>method.java.lang.Thread.getId</string>
					<string/>
				</void>
				
				<void method="addDefaultSecurityPermission">
					<string>runtime</string>
					<string>method.java.lang.reflect.Type.*</string>
					<string/>
				</void>

				<void method="addDefaultSecurityPermission">
					<string>runtime</string>
					<string>method.java.lang.reflect.InvocationTargetException.*</string>
					<string/>
				</void>

				<void method="addDefaultSecurityPermission">
					<string>runtime</string>
					<string>method.java.lang.reflect.ReflectPermission.*</string>
					<string/>
				</void>

				<void method="addDefaultSecurityPermission">
					<string>runtime</string>
					<string>method.java.net.SocketPermission.*</string>
					<string/>
				</void>

				<void method="addDefaultSecurityPermission">
					<string>runtime</string>
					<string>method.java.net.InetAddress.*</string>
					<string/>
				</void>

				<void method="addDefaultSecurityPermission">
					<string>runtime</string>
					<string>method.java.net.Inet4Address.*</string>
					<string/>
				</void>

				<void method="addDefaultSecurityPermission">
					<string>runtime</string>
					<string>method.java.net.Inet6Address.*</string>
					<string/>
				</void>

				<void method="addDefaultSecurityPermission">
					<string>runtime</string>
					<string>method.java.net.URISyntaxException.*</string>
					<string/>
				</void>

				<void method="addDefaultSecurityPermission">
					<string>runtime</string>
					<string>method.java.net.MalformedURLException.*</string>
					<string/>
				</void>
		
				<void method="addDefaultSecurityPermission">
					<string>runtime</string>
					<string>method.java.net.URI.*</string>
					<string/>
				</void>

				<void method="addDefaultSecurityPermission">
					<string>runtime</string>
					<string>method.java.net.URL.*</string>
					<string/>
				</void>
		
				<void method="addDefaultSecurityPermission">
					<string>runtime</string>
					<string>method.java.io.DataInputStream.*</string>
					<string/>
				</void>

				<void method="addDefaultSecurityPermission">
					<string>runtime</string>
					<string>method.java.io.DataOutputStream.*</string>
					<string/>
				</void>

				<void method="addDefaultSecurityPermission">
					<string>runtime</string>
					<string>method.java.io.FilePermission.*</string>
					<string/>
				</void>
		
				<void method="addDefaultSecurityPermission">
					<string>runtime</string>
					<string>method.java.io.BufferedWriter.*</string>
					<string/>
				</void>

				<void method="addDefaultSecurityPermission">
					<string>runtime</string>
					<string>method.java.io.BufferedReader.*</string>
					<string/>
				</void>

				<void method="addDefaultSecurityPermission">
					<string>runtime</string>
					<string>method.java.io.StringWriter.*</string>
					<string/>
				</void>
		
				<void method="addDefaultSecurityPermission">
					<string>runtime</string>
					<string>method.java.io.StringReader.*</string>
					<string/>
				</void>

				<void method="addDefaultSecurityPermission">
					<string>runtime</string>
					<string>method.java.io.BufferedInputStream.*</string>
					<string/>
				</void>

				<void method="addDefaultSecurityPermission">
					<string>runtime</string>
					<string>method.java.io.BufferedOutputStream.*</string>
					<string/>
				</void>
		
				<void method="addDefaultSecurityPermission">
					<string>runtime</string>
					<string>method.java.io.ByteArrayInputStream.*</string>
					<string/>
				</void>

				<void method="addDefaultSecurityPermission">
					<string>runtime</string>
					<string>method.java.io.ByteArrayOutputStream.*</string>
					<string/>
				</void>

				<void method="addDefaultSecurityPermission">
					<string>runtime</string>
					<string>method.java.io.Serializable.*</string>
					<string/>
				</void>

				<void method="addDefaultSecurityPermission">
					<string>runtime</string>
					<string>method.java.io.IOException.*</string>
					<string/>
				</void>

				<void method="addDefaultSecurityPermission">
					<string>runtime</string>
					<string>method.java.io.InputStream.*</string>
					<string/>
				</void>

				<void method="addDefaultSecurityPermission">
					<string>runtime</string>
					<string>method.java.io.OutputStream.*</string>
					<string/>
				</void>

				<void method="addDefaultSecurityPermission">
					<string>runtime</string>
					<string>method.java.io.ObjectInputStream.*</string>
					<string/>
				</void>

				<void method="addDefaultSecurityPermission">
					<string>runtime</string>
					<string>method.java.io.ObjectOutputStream.*</string>
					<string/>
				</void>

				<void method="addDefaultSecurityPermission">
					<string>runtime</string>
					<string>method.java.io.UnsupportedEncodingException.*</string>
					<string/>
				</void>

				<void method="addDefaultSecurityPermission">
					<string>runtime</string>
					<string>method.java.io.ObjectInputStream.*</string>
					<string/>
				</void>

				<void method="addDefaultSecurityPermission">
					<string>runtime</string>
					<string>method.java.io.ObjectOutputStream.*</string>
					<string/>
				</void>

				<void method="addDefaultSecurityPermission">
					<string>runtime</string>
					<string>method.java.io.UnsupportedEncodingException.*</string>
					<string/>
				</void>

				<void method="addDefaultSecurityPermission">
					<string>runtime</string>
					<string>method.java.io.InvalidObjectException.*</string>
					<string/>
				</void>

				<void method="addDefaultSecurityPermission">
					<string>runtime</string>
					<string>method.java.io.Reader.*</string>
					<string/>
				</void>

				<void method="addDefaultSecurityPermission">
					<string>runtime</string>
					<string>method.java.io.Writer.*</string>
					<string/>
				</void>
		
				<void method="addDefaultSecurityPermission">
					<string>runtime</string>
					<string>method.java.io.PrintWriter.*</string>
					<string/>
				</void>

				<void method="addDefaultSecurityPermission">
					<string>runtime</string>
					<string>method.java.io.PrintStream.*</string>
					<string/>
				</void>

				<void method="addDefaultSecurityPermission">
					<string>runtime</string>
					<string>method.java.io.InputStreamReader.*</string>
					<string/>
				</void>

				<void method="addDefaultSecurityPermission">
					<string>runtime</string>
					<string>method.java.io.OutputStreamWriter.*</string>
					<string/>
				</void>

				<void method="addDefaultSecurityPermission">
					<string>runtime</string>
					<string>method.java.io.FileNotFoundException.*</string>
					<string/>
				</void>

				<void method="addDefaultSecurityPermission">
					<string>runtime</string>
					<string>method.java.io.EOFException.*</string>
					<string/>
				</void>

				<void method="addDefaultSecurityPermission">
					<string>runtime</string>
					<string>method.java.io.Flushable.*</string>
					<string/>
				</void>
		
				<void method="addDefaultSecurityPermission">
					<string>runtime</string>
					<string>method.java.io.Closeable.*</string>
					<string/>
				</void>
				
			</object>
		</void>

		<void property="pluginManager">
			<object class="br.com.uoutec.ediacaran.core.PluginManagerImp"/>
		</void>

		<void property="pluginConfigurationFileReader">
			<object class="br.com.uoutec.ediacaran.core.plugins.PluginConfigurationFileReaderImp"/>
		</void>

		<void property="pluginManagerData">
			<object class="br.com.uoutec.ediacaran.core.PluginManagerDataImp"/>
		</void>
		
		<void property="pluginConfigurationFileWriter">
			<object class="br.com.uoutec.ediacaran.core.plugins.PluginConfigurationFileWriterImp"/>
		</void>

		<void property="exportImportPlugins">
			<object class="br.com.uoutec.ediacaran.core.plugins.ExportImportPluginsImp"/>
		</void>

		<void property="pluginInitializer">
			<object class="br.com.uoutec.ediacaran.weld.plugin.BuilderPluginInitializer">
			    <!--
				<void method="addService">
					<string>br.com.uoutec.ediacaran.weld.WeldEdiacaranThreadPoolExecutorServices</string>
				</void>
				-->
				<!--
				<void method="addExtension">
					<string>com.arjuna.ats.jta.cdi.TransactionExtension</string>
				</void>
				<void method="addExtension">
					<string>br.com.uoutec.filter.invoker.cdi.InvokerFilterExtension</string>
				</void>
				-->
			</object>
		</void>

		<void property="pluginsSuppliersFactory">
			<object class="br.com.uoutec.ediacaran.core.plugins.PluginsSuppliersFactoryImp"/>
		</void>
	
		<void property="pluginInstaller">
			<object class="br.com.uoutec.ediacaran.core.plugins.PluginInstallerImp"/>
		</void>

		<void property="pluginClassLoaderFactory">
			<object class="br.com.uoutec.ediacaran.web.tomcat.TomcatBuilderClassLoaderFactory">
				<!--
				<void method="addIncludePluginClassPathMatch">
					<string>.*persistence.*</string>
				</void>
				<void method="addIncludePluginClassPathMatch">
					<string>.*plugin.*</string>
				</void>
				<void method="addIncludePluginClassPathMatch">
					<string>.*filter.*</string>
				</void>
				-->
				
				<!--				
				<void method="addIncludePluginClassPathMatch">
					<string>front-security</string>
					<string>.*front-security.*</string>
				</void>
				
				<void method="addIncludePluginClassPathMatch">
					<string>web</string>
					<string>.*web-plugin.*</string>
				</void>
				
				<void method="addIncludePluginClassPathMatch">
					<string>security</string>
					<string>.*security.*</string>
				</void>
				
				<void method="addIncludePluginClassPathMatch">
					<string>system</string>
					<string>.*system-ediacaran.*</string>
				</void>
				
				<void method="addIncludePluginClassPathMatch">
					<string>front</string>
					<string>.*front-ediacaran.*</string>
				</void>
				
				<void method="addIncludePluginClassPathMatch">
					<string>test</string>
					<string>.*ediacaran-test.*</string>
				</void>
				-->
			</object>
		</void>
		
		<!--  
		<void property="parentClassLoader">
			<object class="java.net.URLClassLoader">
				...
			</object>
		</void>
		-->
		
		<void property="pluginsLoader">
			<object class="br.com.uoutec.ediacaran.core.plugins.PluginsLoaderImp"/>
		</void>

		<void property="varParser">
			<object class="br.com.uoutec.ediacaran.core.VarParserConfigurationImp">
			
				<void property="useDefaultVars">
					<boolean>true</boolean>
				</void>
			
				<!--
				<void method="registerVarResolver">
					<string>teste</string>
					<object class="br.com.uoutec.ediacaran.weld.VarParserImp"/>
				</void>
				-->
				
			</object>
		</void>

		<void method="addPluginSearch">
			<object class="br.com.uoutec.ediacaran.core.plugins.JarPluginsSearch">
			
				<void property="exportImportPlugins">
					<object class="br.com.uoutec.ediacaran.core.plugins.ExportImportPluginsImp"/>
				</void>
			
			</object>
		</void>

		<void method="addPluginSearch">
			<object class="br.com.uoutec.ediacaran.core.plugins.FileSystemPluginsSearch"/>
		</void>

		<void method="addEntity">
			<object class="br.com.uoutec.ediacaran.web.SecurityProviderImp"/>
			<array class="java.lang.Class" length="0"/>
		</void>
		
		<void method="setSystemProperty">
			<string>java.security.auth.login.config</string>
			<string>C:/develop/ediacaran/config/jaas.config</string>
		</void>
		
		<void method="setSystemProperty">
			<string>java.security.debug</string>
			<string>all</string>
		</void>
		
		<!-- 
		<void method="setSystemProperty">
			<string>java.util.logging.manager</string>
			<string>org.apache.logging.log4j.jul.LogManager</string>
		</void>
		-->	
	</object>
</java>
